MANIFEST.in
README.rst
setup.py
tw2/__init__.py
tw2.captcha.egg-info/PKG-INFO
tw2.captcha.egg-info/SOURCES.txt
tw2.captcha.egg-info/dependency_links.txt
tw2.captcha.egg-info/entry_points.txt
tw2.captcha.egg-info/namespace_packages.txt
tw2.captcha.egg-info/not-zip-safe
tw2.captcha.egg-info/requires.txt
tw2.captcha.egg-info/top_level.txt
tw2/captcha/__init__.py
tw2/captcha/model.py
tw2/captcha/samples.py
tw2/captcha/validators.py
tw2/captcha/widgets.py
tw2/captcha/plugins/__init__.py
tw2/captcha/plugins/image/__init__.py
tw2/captcha/plugins/image/fred.py
tw2/captcha/plugins/image/mcdermott.py
tw2/captcha/plugins/image/vanasco_dowty/__init__.py
tw2/captcha/plugins/image/vanasco_dowty/captcha.py
tw2/captcha/plugins/text/__init__.py
tw2/captcha/plugins/text/fivelettername.py
tw2/captcha/plugins/text/random_ascii.py
tw2/captcha/plugins/text/random_equation.py
tw2/captcha/static/ext/captcha.css
tw2/captcha/static/fonts/tuffy/LICENSE.txt
tw2/captcha/static/fonts/tuffy/Tuffy.ttf
tw2/captcha/static/fonts/tuffy/Tuffy_Bold.ttf
tw2/captcha/static/fonts/tuffy/Tuffy_Bold_Italic.ttf
tw2/captcha/static/fonts/tuffy/Tuffy_Italic.ttf
tw2/captcha/static/images/gnome_audio_volume_medium.png
tw2/captcha/templates/__init__.py
tw2/captcha/templates/captcha.mak