Metadata-Version: 1.0
Name: tw2.captcha
Version: 0.0.3
Summary: toscawidgets2 captcha plugin
Home-page: http://github.com/ralphbean/tw2.captcha
Author: Ralph Bean
Author-email: rbean@redhat.com
License: UNKNOWN
Keywords: toscawidgets.widgets
Platform: UNKNOWN
Classifier: Development Status :: 3 - Alpha
Classifier: Environment :: Web Environment
Classifier: Environment :: Web Environment :: ToscaWidgets
Classifier: Topic :: Software Development :: Libraries :: Python Modules
Classifier: Topic :: Software Development :: Widget Sets
Classifier: Intended Audience :: Developers
Classifier: Operating System :: OS Independent
Classifier: Programming Language :: Python
